<?xml version="1.0" encoding="UTF-8"?>
<BaliMessageLog>
    <Task name="Lattice_Synthesis">
        <Message>
            <ID>2029993</ID>
            <Severity>Warning</Severity>
            <Dynamic>synthesis: Using default loop_limit value of 1950</Dynamic>
            <Navigation>synthesis</Navigation>
            <Navigation>Using default loop_limit value of 1950</Navigation>
        </Message>
        <Message>
            <ID>35001611</ID>
            <Severity>Warning</Severity>
        </Message>
        <Message>
            <ID>1166052</ID>
            <Severity>Warning</Severity>
            <Dynamic>logical</Dynamic>
            <Dynamic>cnt_237_add_4_1/S0</Dynamic>
        </Message>
        <Message>
            <ID>1166052</ID>
            <Severity>Warning</Severity>
            <Dynamic>logical</Dynamic>
            <Dynamic>cnt_237_add_4_11/CO</Dynamic>
        </Message>
        <Message>
            <ID>1166052</ID>
            <Severity>Warning</Severity>
            <Dynamic>logical</Dynamic>
            <Dynamic>cnt_237_add_4_11/S1</Dynamic>
        </Message>
        <Message>
            <ID>1163101</ID>
            <Severity>Warning</Severity>
            <Dynamic>3</Dynamic>
        </Message>
    </Task>
    <Task name="PAR">
        <Message>
            <ID>61061008</ID>
            <Severity>Warning</Severity>
            <Dynamic>clk_c</Dynamic>
            <Dynamic>Primary</Dynamic>
            <Dynamic>clk</Dynamic>
            <Dynamic>33</Dynamic>
            <Dynamic>Primary</Dynamic>
        </Message>
        <Message>
            <ID>61061008</ID>
            <Severity>Warning</Severity>
            <Dynamic>latch_c</Dynamic>
            <Dynamic>Primary</Dynamic>
            <Dynamic>latch</Dynamic>
            <Dynamic>35</Dynamic>
            <Dynamic>Primary</Dynamic>
        </Message>
        <Message>
            <ID>62061008</ID>
            <Severity>Warning</Severity>
            <Dynamic>clk_c</Dynamic>
        </Message>
        <Message>
            <ID>62061008</ID>
            <Severity>Warning</Severity>
            <Dynamic>latch_c</Dynamic>
        </Message>
        <Message>
            <ID>66011008</ID>
            <Severity>Warning</Severity>
            <Dynamic>
   Signal=n1378 loads=2 clock_loads=2</Dynamic>
        </Message>
        <Message>
            <ID>66011008</ID>
            <Severity>Warning</Severity>
            <Dynamic>
   Signal=n1378 loads=2 clock_loads=2</Dynamic>
        </Message>
    </Task>
</BaliMessageLog>